README.rst
setup.py
randpw/__init__.py
randpw/randpw.py
randpw.egg-info/PKG-INFO
randpw.egg-info/SOURCES.txt
randpw.egg-info/dependency_links.txt
randpw.egg-info/entry_points.txt
randpw.egg-info/top_level.txt
randpw/wordlists/en.txt
randpw/wordlists/pt-br.txt