Metadata-Version: 1.0
Name: randpw
Version: 0.4.0
Summary: Random password and passphrase generator
Home-page: https://github.com/pdrb/randpw
Author: Pedro Buteri Gonring
Author-email: pedro@bigode.net
License: MIT
Keywords: random password passphrase generator
Platform: UNKNOWN
